fast_snippets/__init__.py
fast_snippets/__pre_init__.py
fast_snippets/_modidx.py
fast_snippets/health.py
fast_snippets-0.1.0.dist-info/licenses/AUTHORS.md
fast_snippets-0.1.0.dist-info/licenses/LICENSE
fast_snippets-0.1.0.dist-info/METADATA
fast_snippets-0.1.0.dist-info/WHEEL
fast_snippets-0.1.0.dist-info/entry_points.txt
fast_snippets-0.1.0.dist-info/top_level.txt
fast_snippets-0.1.0.dist-info/RECORD
