Metadata-Version: 2.4
Name: fast_snippets
Version: 0.1.0
Summary: Fast Snippets for Pytorch, Computer Vision, Deep Learning and Python in General
Author-email: Yeshwanth Reddy <1992chinna@gmail.com>
Maintainer-email: Yeshwanth Reddy <1992chinna@gmail.com>
License: MIT license
Project-URL: bugs, https://github.com/sizhky/fast_snippets/issues
Project-URL: changelog, https://github.com/sizhky/fast_snippets/blob/master/changelog.md
Project-URL: homepage, https://github.com/sizhky/fast_snippets
License-File: LICENSE
License-File: AUTHORS.md
Requires-Dist: typer
Requires-Dist: nbdev
Requires-Dist: twine>=6.2.0
Provides-Extra: dev
Requires-Dist: coverage; extra == "dev"
Requires-Dist: mypy; extra == "dev"
Requires-Dist: pytest; extra == "dev"
Requires-Dist: ruff; extra == "dev"
Dynamic: license-file
